flask_rbac_icdc/TEST.py
flask_rbac_icdc/__init__.py
flask_rbac_icdc/rbac.py
flask_rbac_icdc/schemes/rbac.json
flask_rbac_icdc-0.1.8.dist-info/licenses/LICENSE
flask_rbac_icdc-0.1.8.dist-info/METADATA
flask_rbac_icdc-0.1.8.dist-info/WHEEL
flask_rbac_icdc-0.1.8.dist-info/top_level.txt
flask_rbac_icdc-0.1.8.dist-info/RECORD
