Metadata-Version: 2.4
Name: flask-rbac-icdc
Version: 0.1.8
Summary: Flask RBAC library using YAML config file
Author-email: ICDC <support@icdc.io>, Vitali Starastsenka <vstarastsenka@ibagroup.eu>
License: MIT License
Project-URL: Homepage, https://github.com/icdc-io/flask-rbac
Project-URL: Repository, https://github.com/icdc-io/flask-rbac.git
Project-URL: Documentation, https://icdc-io.github.io/flask-rbac-docs
Keywords: flask,rbac,yaml,icdc
Classifier: Development Status :: 4 - Beta
Classifier: Programming Language :: Python :: 3
Classifier: Framework :: Flask
Classifier: Operating System :: OS Independent
License-File: LICENSE
Requires-Dist: Flask
Requires-Dist: PyYAML
Requires-Dist: jsonschema
Dynamic: license-file
